splinaltap/LICENSE
splinaltap/README.md
splinaltap/__init__.py
splinaltap/__main__.py
splinaltap/backends.py
splinaltap/cli.py
splinaltap/expression.py
splinaltap/knot.py
splinaltap/methods.py
splinaltap/solver.py
splinaltap/spline.py
splinaltap/spline_group.py
splinaltap/visualization.py
splinaltap-1.0.0.dist-info/METADATA
splinaltap-1.0.0.dist-info/WHEEL
splinaltap-1.0.0.dist-info/entry_points.txt
splinaltap-1.0.0.dist-info/top_level.txt
splinaltap-1.0.0.dist-info/RECORD
