Metadata-Version: 2.2
Name: splinaltap
Version: 1.0.0
Summary: Keyframe interpolation and expression evaluation that goes to eleven!
Home-page: https://github.com/chrisdreid/splinaltap
Author: chris
Author-email: Chris <no-reply@example.com>
License: MIT License
Project-URL: Homepage, https://github.com/chrisdreid/splinaltap
Project-URL: Bug Tracker, https://github.com/chrisdreid/splinaltap/issues
Classifier: Programming Language :: Python :: 3
Classifier: License :: OSI Approved :: MIT License
Classifier: Operating System :: OS Independent
Requires-Python: >=3.7
Provides-Extra: numpy
Requires-Dist: numpy>=1.20.0; extra == "numpy"
Provides-Extra: visualize
Requires-Dist: matplotlib>=3.5.0; extra == "visualize"
Requires-Dist: numpy>=1.20.0; extra == "visualize"
Provides-Extra: gpu
Requires-Dist: jax>=0.3.0; extra == "gpu"
Requires-Dist: jaxlib>=0.3.0; extra == "gpu"
Requires-Dist: cupy>=10.0.0; extra == "gpu"
Provides-Extra: numba
Requires-Dist: numba>=0.55.0; extra == "numba"
Requires-Dist: numpy>=1.20.0; extra == "numba"
Provides-Extra: all
Requires-Dist: numpy>=1.20.0; extra == "all"
Requires-Dist: matplotlib>=3.5.0; extra == "all"
Requires-Dist: jax>=0.3.0; extra == "all"
Requires-Dist: jaxlib>=0.3.0; extra == "all"
Requires-Dist: cupy>=10.0.0; extra == "all"
Requires-Dist: numba>=0.55.0; extra == "all"
Dynamic: author
Dynamic: home-page
Dynamic: requires-python
